pallas/__init__.py
pallas/__main__.py
pallas/asset.py
pallas/response.py
pallas/actions/Fetching.py
pallas/actions/Saving.py
pallas/utils/Assets.py
pallas/utils/Audience.py
pallas/utils/DeviceType.py
pallas/utils/FileManager.py
pallas/utils/OSTrainDevicePair.py
pallas/utils/PallasRequest.py
pallas_py-2025.8.5.dist-info/licenses/LICENSE
pallas_py-2025.8.5.dist-info/METADATA
pallas_py-2025.8.5.dist-info/WHEEL
pallas_py-2025.8.5.dist-info/top_level.txt
pallas_py-2025.8.5.dist-info/RECORD
