Metadata-Version: 2.4
Name: pallas.py
Version: 2025.8.5
Author-email: "@Riigess" <56428356+Riigess@users.noreply.github.com>
License: MIT License
Project-URL: Documentation, https://github.com/Riigess/pallas.py/tree/library/docs
Project-URL: Repository, https://github.com/Riigess/pallas.py
Project-URL: Issues, https://github.com/Riigess/pallas.py/issues
Keywords: apple,pallas,mobiledevice,mobile device,ios,macos,siri,tvos,xros,visionos
Classifier: Topic :: Software Development :: Libraries
Classifier: Topic :: Software Development :: Libraries :: Python Modules
Classifier: License :: OSI Approved :: MIT License
Classifier: Programming Language :: Python :: 3.9
Classifier: Programming Language :: Python :: 3.10
Classifier: Programming Language :: Python :: 3.11
Classifier: Programming Language :: Python :: 3.12
Classifier: Programming Language :: Python :: 3.13
Classifier: Programming Language :: Python :: 3.14
Requires-Python: >=3.9
License-File: LICENSE
Dynamic: license-file
